picture_cutter/__init__.py
picture_cutter/cutter.py
picture_cutter-0.0.1.dist-info/LICENSE
picture_cutter-0.0.1.dist-info/METADATA
picture_cutter-0.0.1.dist-info/WHEEL
picture_cutter-0.0.1.dist-info/top_level.txt
picture_cutter-0.0.1.dist-info/RECORD
