Metadata-Version: 2.1
Name: picture-cutter
Version: 0.0.1
Summary: Package to cut picture
Home-page: https://github.com/debuglevel/picture_cutter
Author: debuglevel
Author-email: debuglevel@gmail.com
License: UNKNOWN
Platform: UNKNOWN
Classifier: Programming Language :: Python :: 3
Classifier: License :: OSI Approved :: MIT License
Classifier: Operating System :: OS Independent
Requires-Python: >=3.6
